relations_iterator/__init__.py
relations_iterator/clone.py
relations_iterator/iterator.py
relations_iterator/relation_tree.py
relations_iterator/visitor.py
django_relations_iterator-0.0.5.dist-info/LICENSE
django_relations_iterator-0.0.5.dist-info/METADATA
django_relations_iterator-0.0.5.dist-info/WHEEL
django_relations_iterator-0.0.5.dist-info/top_level.txt
django_relations_iterator-0.0.5.dist-info/RECORD
