Metadata-Version: 2.1
Name: django-relations-iterator
Version: 0.0.5
Summary: Tool to iterate over django relation tree
Home-page: https://github.com/regqueryvalueex/django-relations-iterator
Author: Alex Zayets
Author-email: alex.consp@gmail.com
Project-URL: Bug Tracker, https://github.com/regqueryvalueex/django-relations-iterator/issues
Classifier: Programming Language :: Python :: 3
Classifier: License :: OSI Approved :: MIT License
Classifier: Operating System :: OS Independent
Requires-Python: >=3.6
License-File: LICENSE
